fpga_pwm_motor/motor.v
module motor(
	input clk,
	input [2:0] switch,
	output reg [2:0] motor
);

parameter cycle_len = 10;
parameter duty0 = 4;
parameter duty1 = 8;

integer counter = 0;
always @(posedge clk) begin
	if (counter < cycle_len) counter <= counter + 1;
	else counter <= 0;
end

always @(*) begin
	motor = 3'd0;
	if (switch[0]) begin
		motor[0] = switch[1] ? 0:1;
		motor[1] = switch[1] ? 1:0;
		motor[2] = (counter < (switch[2] ? duty1:duty0)) ? 1'b1:1'b0;
	end
end
endmodule

fpga_pwm_motor/tb_motor.v
`timescale 1ns / 1ps
`include "motor.v"

module motor_tb;

reg clk;
reg [2:0] switch;

wire [2:0] motor;

motor uut (
    .clk(clk),
    .switch(switch),
    .motor(motor)
);

initial clk = 0;
always #10 clk = ~clk;

initial begin
	$dumpfile("final.vcd");
	$dumpvars(0, motor_tb);

    switch = 3'b000;
    #400;

    switch = 3'b001;
    #400;

    switch = 3'b101;
    #400;

    switch = 3'b011;
    #400;

    switch = 3'b111;
    #400;

    $finish;
end

endmodule

fpga_pwm_motor/final.vcd
$date
	Sun Feb  1 15:05:22 2026
$end
$version
	Icarus Verilog
$end
$timescale
	1ps
$end
$scope module motor_tb $end
$var wire 3 ! motor [2:0] $end
$var reg 1 " clk $end
$var reg 3 # switch [2:0] $end
$scope module uut $end
$var wire 1 " clk $end
$var wire 3 $ switch [2:0] $end
$var parameter 32 % cycle_len $end
$var parameter 32 & duty0 $end
$var parameter 32 ' duty1 $end
$var reg 3 ( motor [2:0] $end
$var integer 32 ) counter [31:0] $end
$upscope $end
$upscope $end
$enddefinitions $end
$comment Show the parameter values. $end
$dumpall
b1000 '
b100 &
b1010 %
$end
#0
$dumpvars
b0 )
b0 (
b0 $
b0 #
0"
b0 !
$end
#10000
b1 )
1"
#20000
0"
#30000
b10 )
1"
#40000
0"
#50000
b11 )
1"
#60000
0"
#70000
b100 )
1"
#80000
0"
#90000
b101 )
1"
#100000
0"
#110000
b110 )
1"
#120000
0"
#130000
b111 )
1"
#140000
0"
#150000
b1000 )
1"
#160000
0"
#170000
b1001 )
1"
#180000
0"
#190000
b1010 )
1"
#200000
0"
#210000
b0 )
1"
#220000
0"
#230000
b1 )
1"
#240000
0"
#250000
b10 )
1"
#260000
0"
#270000
b11 )
1"
#280000
0"
#290000
b100 )
1"
#300000
0"
#310000
b101 )
1"
#320000
0"
#330000
b110 )
1"
#340000
0"
#350000
b111 )
1"
#360000
0"
#370000
b1000 )
1"
#380000
0"
#390000
b1001 )
1"
#400000
b1 !
b1 (
0"
b1 #
b1 $
#410000
b1 !
b1 (
b1010 )
1"
#420000
0"
#430000
b101 !
b101 (
b0 )
1"
#440000
0"
#450000
b101 !
b101 (
b1 )
1"
#460000
0"
#470000
b101 !
b101 (
b10 )
1"
#480000
0"
#490000
b101 !
b101 (
b11 )
1"
#500000
0"
#510000
b1 !
b1 (
b100 )
1"
#520000
0"
#530000
b1 !
b1 (
b101 )
1"
#540000
0"
#550000
b1 !
b1 (
b110 )
1"
#560000
0"
#570000
b1 !
b1 (
b111 )
1"
#580000
0"
#590000
b1 !
b1 (
b1000 )
1"
#600000
0"
#610000
b1 !
b1 (
b1001 )
1"
#620000
0"
#630000
b1 !
b1 (
b1010 )
1"
#640000
0"
#650000
b101 !
b101 (
b0 )
1"
#660000
0"
#670000
b101 !
b101 (
b1 )
1"
#680000
0"
#690000
b101 !
b101 (
b10 )
1"
#700000
0"
#710000
b101 !
b101 (
b11 )
1"
#720000
0"
#730000
b1 !
b1 (
b100 )
1"
#740000
0"
#750000
b1 !
b1 (
b101 )
1"
#760000
0"
#770000
b1 !
b1 (
b110 )
1"
#780000
0"
#790000
b1 !
b1 (
b111 )
1"
#800000
b101 !
b101 (
0"
b101 #
b101 $
#810000
b1 !
b1 (
b1000 )
1"
#820000
0"
#830000
b1 !
b1 (
b1001 )
1"
#840000
0"
#850000
b1 !
b1 (
b1010 )
1"
#860000
0"
#870000
b101 !
b101 (
b0 )
1"
#880000
0"
#890000
b101 !
b101 (
b1 )
1"
#900000
0"
#910000
b101 !
b101 (
b10 )
1"
#920000
0"
#930000
b101 !
b101 (
b11 )
1"
#940000
0"
#950000
b101 !
b101 (
b100 )
1"
#960000
0"
#970000
b101 !
b101 (
b101 )
1"
#980000
0"
#990000
b101 !
b101 (
b110 )
1"
#1000000
0"
#1010000
b101 !
b101 (
b111 )
1"
#1020000
0"
#1030000
b1 !
b1 (
b1000 )
1"
#1040000
0"
#1050000
b1 !
b1 (
b1001 )
1"
#1060000
0"
#1070000
b1 !
b1 (
b1010 )
1"
#1080000
0"
#1090000
b101 !
b101 (
b0 )
1"
#1100000
0"
#1110000
b101 !
b101 (
b1 )
1"
#1120000
0"
#1130000
b101 !
b101 (
b10 )
1"
#1140000
0"
#1150000
b101 !
b101 (
b11 )
1"
#1160000
0"
#1170000
b101 !
b101 (
b100 )
1"
#1180000
0"
#1190000
b101 !
b101 (
b101 )
1"
#1200000
b10 !
b10 (
0"
b11 #
b11 $
#1210000
b10 !
b10 (
b110 )
1"
#1220000
0"
#1230000
b10 !
b10 (
b111 )
1"
#1240000
0"
#1250000
b10 !
b10 (
b1000 )
1"
#1260000
0"
#1270000
b10 !
b10 (
b1001 )
1"
#1280000
0"
#1290000
b10 !
b10 (
b1010 )
1"
#1300000
0"
#1310000
b110 !
b110 (
b0 )
1"
#1320000
0"
#1330000
b110 !
b110 (
b1 )
1"
#1340000
0"
#1350000
b110 !
b110 (
b10 )
1"
#1360000
0"
#1370000
b110 !
b110 (
b11 )
1"
#1380000
0"
#1390000
b10 !
b10 (
b100 )
1"
#1400000
0"
#1410000
b10 !
b10 (
b101 )
1"
#1420000
0"
#1430000
b10 !
b10 (
b110 )
1"
#1440000
0"
#1450000
b10 !
b10 (
b111 )
1"
#1460000
0"
#1470000
b10 !
b10 (
b1000 )
1"
#1480000
0"
#1490000
b10 !
b10 (
b1001 )
1"
#1500000
0"
#1510000
b10 !
b10 (
b1010 )
1"
#1520000
0"
#1530000
b110 !
b110 (
b0 )
1"
#1540000
0"
#1550000
b110 !
b110 (
b1 )
1"
#1560000
0"
#1570000
b110 !
b110 (
b10 )
1"
#1580000
0"
#1590000
b110 !
b110 (
b11 )
1"
#1600000
b110 !
b110 (
0"
b111 #
b111 $
#1610000
b110 !
b110 (
b100 )
1"
#1620000
0"
#1630000
b110 !
b110 (
b101 )
1"
#1640000
0"
#1650000
b110 !
b110 (
b110 )
1"
#1660000
0"
#1670000
b110 !
b110 (
b111 )
1"
#1680000
0"
#1690000
b10 !
b10 (
b1000 )
1"
#1700000
0"
#1710000
b10 !
b10 (
b1001 )
1"
#1720000
0"
#1730000
b10 !
b10 (
b1010 )
1"
#1740000
0"
#1750000
b110 !
b110 (
b0 )
1"
#1760000
0"
#1770000
b110 !
b110 (
b1 )
1"
#1780000
0"
#1790000
b110 !
b110 (
b10 )
1"
#1800000
0"
#1810000
b110 !
b110 (
b11 )
1"
#1820000
0"
#1830000
b110 !
b110 (
b100 )
1"
#1840000
0"
#1850000
b110 !
b110 (
b101 )
1"
#1860000
0"
#1870000
b110 !
b110 (
b110 )
1"
#1880000
0"
#1890000
b110 !
b110 (
b111 )
1"
#1900000
0"
#1910000
b10 !
b10 (
b1000 )
1"
#1920000
0"
#1930000
b10 !
b10 (
b1001 )
1"
#1940000
0"
#1950000
b10 !
b10 (
b1010 )
1"
#1960000
0"
#1970000
b110 !
b110 (
b0 )
1"
#1980000
0"
#1990000
b110 !
b110 (
b1 )
1"
