alu_8bit/alu_8bit.sv
module alu_8bit (
    input  logic [7:0] A,
    input  logic [7:0] B,
    input  logic [3:0] ALU_Sel,
    output logic [7:0] Result,
    output logic Carry,
    output logic Zero,
    output logic Overflow
);

    logic [8:0] temp;

    always @(*) begin
        // defaults
        Result   = 8'b0;
        Carry    = 1'b0;
        Overflow = 1'b0;

        case (ALU_Sel)
            4'b0000: begin
                temp     = A + B;
                Result   = temp[7:0];
                Carry    = temp[8];
                Overflow = (~(A[7] ^ B[7])) & (A[7] ^ Result[7]);
            end

            4'b0001: begin
                temp     = A - B;
                Result   = temp[7:0];
                Carry    = temp[8];
                Overflow = ((A[7] ^ B[7])) & (A[7] ^ Result[7]);
            end

            4'b0010: Result = A & B;
            4'b0011: Result = A | B;
            4'b0100: Result = A ^ B;
            4'b0101: Result = ~A;
            4'b0110: Result = A << 1;
            4'b0111: Result = A >> 1;

            default: Result = 8'b0;
        endcase
    end

    assign Zero = (Result == 8'b0);

endmodule

alu_8bit/tb_alu_8bit.sv
`timescale 1ns/1ps

module tb_alu_8bit;

    logic [7:0] A, B;
    logic [3:0] ALU_Sel;
    logic [7:0] Result;
    logic Carry, Zero, Overflow;

    // Instantiate DUT
    alu_8bit dut (
        .A(A),
        .B(B),
        .ALU_Sel(ALU_Sel),
        .Result(Result),
        .Carry(Carry),
        .Zero(Zero),
        .Overflow(Overflow)
    );

    initial begin
		$dumpfile("wave.vcd");
        $dumpvars(0, tb_alu_8bit);

		$monitor("A=%b B=%b Sel=%b | R=%b C=%b V=%b Z=%b",
        A, B, ALU_Sel, Result, Carry, Overflow, Zero);

        // ADD (no overflow)
        A = 8'd10; B = 8'd20; ALU_Sel = 4'b0000; #10;

        // ADD (signed overflow)
        A = 8'd127; B = 8'd1; ALU_Sel = 4'b0000; #10;

        // SUB
        A = 8'd10; B = 8'd20; ALU_Sel = 4'b0001; #10;

        // AND
        A = 8'hAA; B = 8'h55; ALU_Sel = 4'b0010; #10;

        // OR
        ALU_Sel = 4'b0011; #10;

        // XOR
        ALU_Sel = 4'b0100; #10;

        // NOT
        ALU_Sel = 4'b0101; #10;

        // SHIFT LEFT
        A = 8'b00001111; ALU_Sel = 4'b0110; #10;

        // SHIFT RIGHT
        ALU_Sel = 4'b0111; #10;

        $finish;
    end

endmodule

alu_8bit/wave.vcd
$date
	Sun Feb  1 15:30:41 2026
$end
$version
	Icarus Verilog
$end
$timescale
	1ps
$end
$scope module tb_alu_8bit $end
$var wire 1 ! Zero $end
$var wire 8 " Result [7:0] $end
$var wire 1 # Overflow $end
$var wire 1 $ Carry $end
$var reg 8 % A [7:0] $end
$var reg 4 & ALU_Sel [3:0] $end
$var reg 8 ' B [7:0] $end
$scope module dut $end
$var wire 8 ( A [7:0] $end
$var wire 4 ) ALU_Sel [3:0] $end
$var wire 8 * B [7:0] $end
$var wire 1 ! Zero $end
$var reg 1 $ Carry $end
$var reg 1 # Overflow $end
$var reg 8 + Result [7:0] $end
$var reg 9 , temp [8:0] $end
$upscope $end
$upscope $end
$enddefinitions $end
$comment Show the parameter values. $end
$dumpall
$end
#0
$dumpvars
b11110 ,
b11110 +
b10100 *
b0 )
b1010 (
b10100 '
b0 &
b1010 %
0$
0#
b11110 "
0!
$end
#10000
1#
b10000000 ,
0!
b10000000 "
b10000000 +
b1 '
b1 *
b1111111 %
b1111111 (
#20000
1$
b111110110 ,
0#
0!
b11110110 "
b11110110 +
b1 &
b1 )
b10100 '
b10100 *
b1010 %
b1010 (
#30000
0$
1!
b0 "
b0 +
b10 &
b10 )
b1010101 '
b1010101 *
b10101010 %
b10101010 (
#40000
0!
b11111111 "
b11111111 +
b11 &
b11 )
#50000
0!
b11111111 "
b11111111 +
b100 &
b100 )
#60000
0!
b1010101 "
b1010101 +
b101 &
b101 )
#70000
0!
b11110 "
b11110 +
b110 &
b110 )
b1111 %
b1111 (
#80000
0!
b111 "
b111 +
b111 &
b111 )
